docs/__init__.py
docs/api/__init__.py
docs/api/apps.py
docs/api/urls.py
docs/apps/__init__.py
docs/apps/home/__init__.py
docs/apps/home/apps.py
docs/apps/home/migrations/0001_initial.py
docs/apps/home/migrations/0002_create_homepage.py
docs/apps/home/migrations/__init__.py
docs/apps/home/models.py
docs/apps/home/tests/__init__.py
docs/apps/home/tests/test_models.py
docs/apps/indexes/__init__.py
docs/apps/indexes/apps.py
docs/apps/indexes/migrations/0001_initial.py
docs/apps/indexes/migrations/0002_alter_docsindex_content.py
docs/apps/indexes/migrations/__init__.py
docs/apps/indexes/models.py
docs/apps/indexes/tests/__init__.py
docs/apps/indexes/tests/test_models.py
docs/apps/pages/__init__.py
docs/apps/pages/apps.py
docs/apps/pages/migrations/0001_initial.py
docs/apps/pages/migrations/0002_initial.py
docs/apps/pages/migrations/0003_alter_docspage_content.py
docs/apps/pages/migrations/0004_alter_docspage_content.py
docs/apps/pages/migrations/0005_formfield_frompage_alter_docspage_content.py
docs/apps/pages/migrations/0006_frompage_tags_formfield_job.py
docs/apps/pages/migrations/0007_alter_docspage_content_alter_frompage_content.py
docs/apps/pages/migrations/__init__.py
docs/apps/pages/models.py
docs/apps/pages/tests/__init__.py
docs/apps/pages/tests/test_models.py
docs/apps/sections/__init__.py
docs/apps/sections/apps.py
docs/apps/sections/migrations/0001_initial.py
docs/apps/sections/migrations/0002_alter_docssection_content.py
docs/apps/sections/migrations/__init__.py
docs/apps/sections/models.py
docs/apps/sections/tests/__init__.py
docs/apps/sections/tests/test_models.py
docs/apps/signals.py
docs/apps/tags/__init__.py
docs/apps/tags/apps.py
docs/apps/tags/migrations/0001_initial.py
docs/apps/tags/migrations/0002_fromtag.py
docs/apps/tags/migrations/__init__.py
docs/apps/tags/models.py
docs/apps.py
docs/cms/__init__.py
docs/cms/apps.py
docs/cms/blocks.py
docs/ui/__init__.py
docs/ui/apps.py
docs/ui/locale/ar/LC_MESSAGES/django.po
django_w_docs-1.0.8.dist-info/METADATA
django_w_docs-1.0.8.dist-info/WHEEL
django_w_docs-1.0.8.dist-info/licenses/LICENSE
django_w_docs-1.0.8.dist-info/RECORD
